microscopeimagequality/__init__.py
microscopeimagequality/application.py
microscopeimagequality/constants.py
microscopeimagequality/data_provider.py
microscopeimagequality/dataset_creation.py
microscopeimagequality/degrade.py
microscopeimagequality/evaluation.py
microscopeimagequality/miq.py
microscopeimagequality/prediction.py
microscopeimagequality/summarize.py
microscopeimagequality/validation.py
microscopeimagequality-0.1.0.dev5.dist-info/DESCRIPTION.rst
microscopeimagequality-0.1.0.dev5.dist-info/METADATA
microscopeimagequality-0.1.0.dev5.dist-info/RECORD
microscopeimagequality-0.1.0.dev5.dist-info/WHEEL
microscopeimagequality-0.1.0.dev5.dist-info/entry_points.txt
microscopeimagequality-0.1.0.dev5.dist-info/metadata.json
microscopeimagequality-0.1.0.dev5.dist-info/top_level.txt
