Metadata-Version: 2.0
Name: microscopeimagequality
Version: 0.1.0.dev5
Summary: Microscope Image Quality Classification
Home-page: https://github.com/google/microscopeimagequality
Author: Samuel Yang
Author-email: samuely@google.com
License: Apache 2.0
Platform: UNKNOWN
Classifier: License :: OSI Approved :: Apache Software License
Classifier: Intended Audience :: Science/Research
Classifier: Programming Language :: Python :: 2.7
Classifier: Topic :: Scientific/Engineering
Requires-Dist: Pillow
Requires-Dist: click
Requires-Dist: matplotlib
Requires-Dist: nose
Requires-Dist: numpy
Requires-Dist: scikit-image
Requires-Dist: scipy
Requires-Dist: six
Requires-Dist: tensorflow
